README.md
setup.py
mistra.egg-info/PKG-INFO
mistra.egg-info/SOURCES.txt
mistra.egg-info/dependency_links.txt
mistra.egg-info/requires.txt
mistra.egg-info/top_level.txt
mistra/core/__init__.py
mistra/core/domains.py
mistra/core/events.py
mistra/core/intervals.py
mistra/core/pricing.py
mistra/core/providers.py
mistra/core/sources.py
mistra/core/timelapses.py
mistra/core/growing_arrays/__init__.py
mistra/core/growing_arrays/support.py
mistra/core/growing_arrays/types.py
mistra/core/indicators/__init__.py
mistra/core/indicators/predictor.py
mistra/core/indicators/slope.py
mistra/core/indicators/mixins/__init__.py
mistra/core/indicators/mixins/predictor.py
mistra/core/indicators/mixins/scored.py
mistra/core/indicators/stats/__init__.py
mistra/core/indicators/stats/mean.py
mistra/core/indicators/stats/variance.py
mistra/core/utils/__init__.py
mistra/core/utils/tail_runners.py
mistra/core/utils/mappers/__init__.py
mistra/core/utils/mappers/candle_pluckers.py
mistra/core/utils/mappers/identity_mappers.py
mistra/core/utils/mappers/row_pluckers.py
mistra/core/utils/mappers/side_pluckers.py
mistra/core/utils/mappers/smart_pluckers.py