Metadata-Version: 2.1
Name: mistra
Version: 0.1.9
Summary: MISTRA (Market InSights / TRading Algorithms) provides core support to market timelapses and indicators management
Home-page: 
Author: luismasuelli
Author-email: luisfmasuelli@gmail.com
License: MIT
Requires-Python: >=3.12
Requires-Dist: numpy>=2.1.3
Requires-Dist: requests>=2.22.0
Requires-Dist: scipy>=1.14.1
